brain_games/__init__.py
brain_games/cli.py
brain_games/games/calc_game.py
brain_games/games/even_game.py
brain_games/games/gcd_game.py
brain_games/is_int.py
brain_games/scripts/__init__.py
brain_games/scripts/brain_calc.py
brain_games/scripts/brain_even.py
brain_games/scripts/brain_games.py
brain_games/scripts/brain_gcd.py
izvekovweb_project_1-0.1.2.dist-info/entry_points.txt
izvekovweb_project_1-0.1.2.dist-info/WHEEL
izvekovweb_project_1-0.1.2.dist-info/METADATA
izvekovweb_project_1-0.1.2.dist-info/RECORD
