Metadata-Version: 2.1
Name: izvekovweb-project-1
Version: 0.1.2
Summary: Игры разума
Author: Alexander Izvekov
Author-email: izvekov.web@yandex.ru
Requires-Python: >=3.8,<4.0
Classifier: Programming Language :: Python :: 3
Classifier: Programming Language :: Python :: 3.10
Classifier: Programming Language :: Python :: 3.8
Classifier: Programming Language :: Python :: 3.9
Requires-Dist: prompt (>=0.4.1,<0.5.0)
